{"version": "3", "templates": [    {
      "id": 73,
      "type": 3,
      "title": "I Hate Money",
      "name": "ihatemoney",
      "description": "I hate money is a web application made to ease shared budget management. It keeps track of who bought what, when, and for whom; and helps to settle the bills.",
      "note": "A simple shared budget manager web application",
      "categories": ["BigBearCasaOS", "selfhosted"],
      "platform": "linux",
      "logo": "https://cdn.jsdelivr.net/gh/selfhst/icons/png/ihatemoney.png",
      "repository": {
        "url": "https://github.com/bigbeartechworld/big-bear-portainer",
        "stackfile": "Apps/ihatemoney/docker-compose.yml"
      },
      "env": [
        {"name": "null", "label": "null", "description": "Sets the secret key environment variable for the application.", "default": ""},
        {"name": "null", "label": "null", "description": "Database connection string.", "default": ""},
        {"name": "null", "label": "null", "description": "Enables the admin dashboard.", "default": ""},
        {"name": "null", "label": "null", "description": "Sets the admin password. On the host run: docker run -it --rm --entrypoint ihatemoney ihatemoney/ihatemoney generate_password_hash", "default": ""},
        {"name": "null", "label": "null", "description": "Disables secure session cookies for development.", "default": ""}
      ]
    }]}
