{"version": "3", "templates": [    {
      "id": 151,
      "type": 3,
      "title": "Piwigo",
      "name": "piwigo",
      "description": "Piwigo is a photo gallery software for the web that comes with powerful features to publish and manage your collection of pictures.",
      "note": "Piwigo",
      "categories": ["BigBearCasaOS", "selfhosted"],
      "platform": "linux",
      "logo": "https://cdn.jsdelivr.net/gh/selfhst/icons/png/piwigo.png",
      "repository": {
        "url": "https://github.com/bigbeartechworld/big-bear-portainer",
        "stackfile": "Apps/piwigo/docker-compose.yml"
      }
    }]}
