{"version": "3", "templates": [    {
      "id": 215,
      "type": 3,
      "title": "What's Up Docker",
      "name": "whats-up-docker",
      "description": "Gets you notified when new versions of your Docker containers are available and lets you react the way you want.",
      "note": "What's Up Docker",
      "categories": ["BigBearCasaOS", "selfhosted"],
      "platform": "linux",
      "logo": "https://cdn.jsdelivr.net/gh/homarr-labs/dashboard-icons/png/whats-up-docker.png",
      "repository": {
        "url": "https://github.com/bigbeartechworld/big-bear-portainer",
        "stackfile": "Apps/whats-up-docker/docker-compose.yml"
      }
    }]}
